{
  "_class": "group",
  "booleanOperation": -1,
  "clippingMaskMode": 0,
  "do_objectID": "C2A4B536-7895-47EF-85D4-D62B5893A3B4",
  "exportOptions": {
    "_class": "exportOptions",
    "do_objectID": "F294DBE1-59CC-46DF-B544-104DBA761D51",
    "exportFormats": [
    ],
    "includedLayerIds": [
    ],
    "layerOptions": 0,
    "shouldTrim": false
  },
  "frame": {
    "_class": "rect",
    "constrainProportions": false,
    "do_objectID": "48BD2DE1-93E3-4A58-BC42-67B59A14EB3A",
    "height": 12,
    "width": 12,
    "x": 134,
    "y": 286
  },
  "groupLayout": {
    "_class": "MSImmutableFreeformGroupLayout",
    "do_objectID": "892AC8F3-285C-423E-8BE8-C2DAB07057C9"
  },
  "hasClickThrough": false,
  "hasClippingMask": false,
  "isFixedToViewport": false,
  "isFlippedHorizontal": false,
  "isFlippedVertical": false,
  "isLocked": false,
  "isVisible": true,
  "layerListExpandedType": 0,
  "layers": [
    {
      "class": "rectangle",
      "id": "F2753740-E245-4ED3-BD69-0C991F66CCEB"
    },
    {
      "class": "shapeGroup",
      "id": "36D5C0D4-5F22-4CE3-BD35-A9ACE080A30C"
    }
  ],
  "name": "Group 11",
  "nameIsFixed": false,
  "resizingConstraint": 63,
  "resizingType": 0,
  "rotation": 0,
  "shouldBreakMaskChain": false,
  "style": {
    "_class": "style",
    "do_objectID": "7E96BFD0-FADA-4B92-9750-BDF3CBE8875D",
    "endMarkerType": 0,
    "miterLimit": 10,
    "startMarkerType": 0,
    "windingRule": 1
  },
  "userInfo": {
    "com.animaapp.stc-sketch-plugin": {
      "kModelPropertiesKey": {
      }
    }
  }
}